{
    "wID": "0",
    "id": "ROOT",
    "children": [
        {
            "wID": "2",
            "form": "ὤφελες",
            "lemma": "ὀφείλω",
            "postag": "v2saia---",
            "head": "0",
            "relation": "PRED",
            "cite": "urn:cts:greekLit:tlg0012.tlg001:3.428",
            "id": "ὤφελες_2",
            "children": [
                {
                    "wID": "1",
                    "form": "ὡς",
                    "lemma": "ὡς",
                    "postag": "d--------",
                    "head": "2",
                    "relation": "AuxY",
                    "cite": "urn:cts:greekLit:tlg0012.tlg001:3.428",
                    "id": "ὡς_1"
                },
                {
                    "wID": "4",
                    "form": "ὀλέσθαι",
                    "lemma": "ὄλλυμι",
                    "postag": "v--anm---",
                    "head": "2",
                    "relation": "OBJ",
                    "cite": "urn:cts:greekLit:tlg0012.tlg001:3.428",
                    "id": "ὀλέσθαι_4",
                    "children": [
                        {
                            "wID": "3",
                            "form": "αὐτόθ'",
                            "lemma": "αὐτόθι",
                            "postag": "d--------",
                            "head": "4",
                            "relation": "ADV",
                            "cite": "urn:cts:greekLit:tlg0012.tlg001:3.428",
                            "id": "αὐτόθ'_3"
                        },
                        {
                            "wID": "6",
                            "form": "δαμεὶς",
                            "lemma": "δαμάζω",
                            "postag": "v-sappmn-",
                            "head": "4",
                            "relation": "ADV",
                            "cite": "urn:cts:greekLit:tlg0012.tlg001:3.429",
                            "id": "δαμεὶς_6",
                            "children": [
                                {
                                    "wID": "5",
                                    "form": "ἀνδρὶ",
                                    "lemma": "ἀνήρ",
                                    "postag": "n-s---md-",
                                    "head": "6",
                                    "relation": "OBJ",
                                    "cite": "urn:cts:greekLit:tlg0012.tlg001:3.429",
                                    "id": "ἀνδρὶ_5",
                                    "children": [
                                        {
                                            "wID": "7",
                                            "form": "κρατερῷ",
                                            "lemma": "κρατερός",
                                            "postag": "a-s---md-",
                                            "head": "5",
                                            "relation": "ATR",
                                            "cite": "urn:cts:greekLit:tlg0012.tlg001:3.429",
                                            "id": "κρατερῷ_7"
                                        },
                                        {
                                            "wID": "13",
                                            "form": "ἦεν",
                                            "lemma": "εἰμί",
                                            "postag": "v3siia---",
                                            "head": "5",
                                            "relation": "ATR",
                                            "cite": "urn:cts:greekLit:tlg0012.tlg001:3.429",
                                            "id": "ἦεν_13",
                                            "children": [
                                                {
                                                    "wID": "8",
                                                    "form": ",",
                                                    "lemma": ",",
                                                    "postag": "u--------",
                                                    "head": "13",
                                                    "relation": "AuxX",
                                                    "cite": "urn:cts:greekLit:tlg0012.tlg001:3.429",
                                                    "id": ",_8"
                                                },
                                                {
                                                    "wID": "9",
                                                    "form": "ὃς",
                                                    "lemma": "ὅς",
                                                    "postag": "p-s---mn-",
                                                    "head": "13",
                                                    "relation": "SBJ",
                                                    "cite": "urn:cts:greekLit:tlg0012.tlg001:3.429",
                                                    "id": "ὃς_9",
                                                    "children": [
                                                        {
                                                            "wID": "11",
                                                            "form": "πρότερος",
                                                            "lemma": "πρότερος",
                                                            "postag": "a-s---mn-",
                                                            "head": "9",
                                                            "relation": "ATV",
                                                            "cite": "urn:cts:greekLit:tlg0012.tlg001:3.429",
                                                            "id": "πρότερος_11"
                                                        }
                                                    ]
                                                },
                                                {
                                                    "wID": "12",
                                                    "form": "πόσις",
                                                    "lemma": "πόσις",
                                                    "postag": "n-s---mn-",
                                                    "head": "13",
                                                    "relation": "PNOM",
                                                    "cite": "urn:cts:greekLit:tlg0012.tlg001:3.429",
                                                    "id": "πόσις_12",
                                                    "children": [
                                                        {
                                                            "wID": "10",
                                                            "form": "ἐμὸς",
                                                            "lemma": "ἐμός",
                                                            "postag": "a-s---mn-",
                                                            "head": "12",
                                                            "relation": "ATR",
                                                            "cite": "urn:cts:greekLit:tlg0012.tlg001:3.429",
                                                            "id": "ἐμὸς_10"
                                                        }
                                                    ]
                                                }
                                            ]
                                        }
                                    ]
                                }
                            ]
                        }
                    ]
                }
            ]
        },
        {
            "wID": "14",
            "form": ".",
            "lemma": ".",
            "postag": "u--------",
            "head": "0",
            "relation": "AuxK",
            "cite": "urn:cts:greekLit:tlg0012.tlg001:3.429",
            "id": "._14"
        }
    ]
}